LICENSE
README.md
setup.py
orthogonalizer/__init__.py
orthogonalizer/app.py
orthogonalizer/utils.py
orthogonalizer.egg-info/PKG-INFO
orthogonalizer.egg-info/SOURCES.txt
orthogonalizer.egg-info/dependency_links.txt
orthogonalizer.egg-info/requires.txt
orthogonalizer.egg-info/top_level.txt
tests/__init__.py
tests/test_app.py