Metadata-Version: 2.1
Name: orthogonalizer
Version: 0.0.4
Summary: A pip installation for orthogonalization of polygons
Home-page: https://github.com/kshitijrajsharma/orthogonalizer
Author: Kshitij Raj Sharma
Author-email: skshitizraj@gmail.com
License: GPL-3.0
Classifier: Development Status :: 3 - Alpha
Classifier: Programming Language :: Python :: 3
Classifier: Programming Language :: Python :: 3.6
Classifier: Programming Language :: Python :: 3.7
Classifier: Programming Language :: Python :: 3.8
Classifier: Programming Language :: Python :: 3.9
License-File: LICENSE
